{"organizations": [], "uuid": "39d035223769af22573625b9b90f0ac358332572", "thread": {"social": {"gplus": {"shares": 0}, "pinterest": {"shares": 0}, "vk": {"shares": 0}, "linkedin": {"shares": 0}, "facebook": {"likes": 0, "shares": 0, "comments": 0}, "stumbledupon": {"shares": 0}}, "site_full": "www.digitalspy.co.uk", "main_image": "http://i1.cdnds.net/15/40/300x225/music-michaels-jackson-03.jpg?76391464", "site_section": "http://www.digitalspy.co.uk/rss/zones/gb/all.xml#", "section_title": "All - Digital Spy - Entertainment and Media News", "url": "http://www.digitalspy.co.uk/ustv/news/a674170/michael-jacksons-final-days-are-being-turned-into-a-tv-show.html?rss", "country": "US", "title": "Michael Jackson's final days are being turned into a TV show - US TV", "performance_score": 0, "site": "digitalspy.co.uk", "participants_count": 3, "title_full": "Michael Jackson's final days are being turned into a TV show - US TV News - Digital Spy", "spam_score": 0.0, "site_type": "news", "published": "2015-10-17T03:00:00.000+03:00", "replies_count": 2, "uuid": "39d035223769af22573625b9b90f0ac358332572"}, "author": "Harry Fletcher", "url": "http://www.digitalspy.co.uk/ustv/news/a674170/michael-jacksons-final-days-are-being-turned-into-a-tv-show.html?rss", "ord_in_thread": 0, "title": "Michael Jackson's final days are being turned into a TV show - US TV", "locations": [], "entities": {"persons": [], "locations": [], "organizations": []}, "highlightText": "", "language": "english", "persons": [], "text": "Michael Jackson's final days are to be the subject of a new TV show.Warner Bros has picked up the rights to an upcoming biography, which focuses on the last 16 weeks of the singer's life. © George De Sota/Redferns via Getty ImagesMichael Jackson Tavis Smiley's book Before You Judge Me… will be released in 2016, centring on the planning stages of Jackson's This Is It concerts.Warner Bros said in a statement that the biography will \"examine the soaring highs and deep lows faced by the late popstar - his constant hunt for privacy in a life that was more public than almost any other, and the pressures he endured as someone whose fame made him socially fragile and almost unable to live\".Jackson died on June 25, 2009 following a cardiac arrest. He had been due to start his run of 50 shows at The O2 in London 18 days later.This year, it was announced that the 'Thriller' star was in talks with George Lucas to play Jar Jar Binks in Star Wars Episode I: The Phantom Menace, but he ultimately lost out to Ahmed Best.Watch the video for Michael Jackson's 'Billie Jean' below:", "external_links": [], "published": "2015-10-17T03:00:00.000+03:00", "crawled": "2015-10-17T09:41:39.074+03:00", "highlightTitle": ""}