{"organizations": [], "uuid": "ac846a605f0dbfe86e208b6f95fd1509c43dd739", "thread": {"social": {"gplus": {"shares": 0}, "pinterest": {"shares": 0}, "vk": {"shares": 0}, "linkedin": {"shares": 0}, "facebook": {"likes": 0, "shares": 0, "comments": 0}, "stumbledupon": {"shares": 0}}, "site_full": "www.newsdump.com", "main_image": "", "site_section": "http://www.newsdump.com/feed/", "section_title": "NewsDump.com, US News, Headlines, Latest USA News, US Sports, US Politics, Football, Business, Celebs, Baseball, Hockey, Basketball", "url": "http://www.newsdump.com/article/death-notices-james-c-masters-iii", "country": "CZ", "title": "Death Notices: James C. Masters III", "performance_score": 0, "site": "newsdump.com", "participants_count": 0, "title_full": "Death Notices: James C. Masters III", "spam_score": 0.0, "site_type": "news", "published": "2015-10-10T07:07:00.000+03:00", "replies_count": 0, "uuid": "ac846a605f0dbfe86e208b6f95fd1509c43dd739"}, "author": "", "url": "http://www.newsdump.com/article/death-notices-james-c-masters-iii", "ord_in_thread": 0, "title": "Death Notices: James C. Masters III", "locations": [], "entities": {"persons": [], "locations": [], "organizations": []}, "highlightText": "", "language": "english", "persons": ["James C. Masters III James C. Masters III", "James C. Masters III"], "text": "James C. Masters III, 73 MUNCIE - James C. Masters III, 73, went home to be with the Lord Thursday, October 8,... ...", "external_links": [], "published": "2015-10-10T07:07:00.000+03:00", "crawled": "2015-10-10T09:15:48.498+03:00", "highlightTitle": ""}