{"organizations": [], "uuid": "a950c3a5e6ac46c94d8dcdf8459bfb3113a05783", "thread": {"social": {"gplus": {"shares": 0}, "pinterest": {"shares": 0}, "vk": {"shares": 0}, "linkedin": {"shares": 0}, "facebook": {"likes": 0, "shares": 0, "comments": 0}, "stumbledupon": {"shares": 0}}, "site_full": "www.bloomberg.com", "main_image": "", "site_section": "http://www.bloomberg.com/personal-finance", "section_title": "Personal-finance - Bloomberg Business", "url": "http://www.bloomberg.com/news/articles/2015-07-21/lexmark-tumbles-after-profit-forecast-misses-analysts-estimates", "country": "US", "title": "Lexmark Tumbles After Profit Forecast Misses Analysts’ Estimates", "performance_score": 0, "site": "bloomberg.com", "participants_count": 1, "title_full": "Lexmark Tumbles After Profit Forecast Misses Analysts’ Estimates - Bloomberg Business", "spam_score": 0.0, "site_type": "news", "published": "2015-07-22T01:23:00.000+03:00", "replies_count": 0, "uuid": "a950c3a5e6ac46c94d8dcdf8459bfb3113a05783"}, "author": "Danielle Muoio", "url": "http://www.bloomberg.com/news/articles/2015-07-21/lexmark-tumbles-after-profit-forecast-misses-analysts-estimates", "ord_in_thread": 0, "title": "Lexmark Tumbles After Profit Forecast Misses Analysts’ Estimates", "locations": [], "entities": {"persons": [], "locations": [], "organizations": []}, "highlightText": "", "language": "english", "persons": [], "text": "Lexmark International Inc. declined the most in almost a decade after reporting a second-quarter loss and forecasting earnings that missed analysts’ estimates.\nLexmark dropped 22 percent to $37.01 at 1:03 p.m. in New York, after earlier falling to $36.36, the biggest intraday decline since October 2005 and the lowest value for the shares in almost 18 months.\nThe printing and imaging company reported a loss of $36.3 million, or 59 cents a share, from a profit of $37.5 million, or 59 cents, a year earlier. Revenue declined 1.4 percent to $879.3 million, missing analysts’ estimates of $901 million.\nLexmark projected earnings in the current quarter, excluding some items, of 51 cents to 61 cents a share compared with analysts’ average estimate of 92 cents. Annual profit is projected in a range of $3.55 to $3.75 a share compared with analysts’ average estimate of $3.78.\nThe Lexington, Kentucky-based company also said it will cut 500 jobs as part of a 2015 restructuring expected to generate pretax savings of $65 million.\n“Despite currency headwinds, we are well positioned to help solve our customer’s unstructured information challenges, as well as attain our goal of $500 million in software revenue and a software operating margin of 25 percent by the end of 2016,” Jerry Grasso, vice president of corporate communications at Lexmark, wrote in an e-mail.\nLexmark said it closed its $954 million acquisition of Kofax Ltd., which produces technologies that converts paper documents into digital images. Lexmark’s shares had increased 16 percent since the purchase was announced March 24 through Monday’s close.", "external_links": [], "published": "2015-07-22T01:23:00.000+03:00", "crawled": "2015-07-21T20:43:11.061+03:00", "highlightTitle": ""}